{
  "games": [
    {
      "title": "8 Bit Panda",
      "id": 10918,
      "consoleId": 65,
      "consoleName": "TIC-80",
      "imageIcon": "/Images/093215.png",
      "numAchievements": 0,
      "numLeaderboards": 0,
      "points": 0,
      "dateModified": null,
      "forumTopicId": null,
      "hashes": []
    },
    {
      "title": "Ball Up",
      "id": 10916,
      "consoleId": 65,
      "consoleName": "TIC-80",
      "imageIcon": "/Images/093216.png",
      "numAchievements": 0,
      "numLeaderboards": 0,
      "points": 0,
      "dateModified": null,
      "forumTopicId": null,
      "hashes": []
    },
    {
      "title": "Balmung",
      "id": 10920,
      "consoleId": 65,
      "consoleName": "TIC-80",
      "imageIcon": "/Images/093217.png",
      "numAchievements": 0,
      "numLeaderboards": 0,
      "points": 0,
      "dateModified": null,
      "forumTopicId": null,
      "hashes": []
    },
    {
      "title": "Bare Bones",
      "id": 10929,
      "consoleId": 65,
      "consoleName": "TIC-80",
      "imageIcon": "/Images/093218.png",
      "numAchievements": 0,
      "numLeaderboards": 0,
      "points": 0,
      "dateModified": null,
      "forumTopicId": null,
      "hashes": []
    },
    {
      "title": "Beyond the Underground",
      "id": 10915,
      "consoleId": 65,
      "consoleName": "TIC-80",
      "imageIcon": "/Images/093219.png",
      "numAchievements": 0,
      "numLeaderboards": 0,
      "points": 0,
      "dateModified": null,
      "forumTopicId": null,
      "hashes": []
    },
    {
      "title": "Cauliflower Power",
      "id": 10928,
      "consoleId": 65,
      "consoleName": "TIC-80",
      "imageIcon": "/Images/093220.png",
      "numAchievements": 0,
      "numLeaderboards": 0,
      "points": 0,
      "dateModified": null,
      "forumTopicId": null,
      "hashes": []
    },
    {
      "title": "Cavern Run",
      "id": 10917,
      "consoleId": 65,
      "consoleName": "TIC-80",
      "imageIcon": "/Images/093221.png",
      "numAchievements": 0,
      "numLeaderboards": 0,
      "points": 0,
      "dateModified": null,
      "forumTopicId": null,
      "hashes": []
    },
    {
      "title": "Doors of Doom",
      "id": 8246,
      "consoleId": 65,
      "consoleName": "TIC-80",
      "imageIcon": "/Images/093222.png",
      "numAchievements": 0,
      "numLeaderboards": 0,
      "points": 0,
      "dateModified": null,
      "forumTopicId": null,
      "hashes": []
    },
    {
      "title": "Everdawn",
      "id": 8247,
      "consoleId": 65,
      "consoleName": "TIC-80",
      "imageIcon": "/Images/093223.png",
      "numAchievements": 0,
      "numLeaderboards": 0,
      "points": 0,
      "dateModified": null,
      "forumTopicId": null,
      "hashes": []
    },
    {
      "title": "Fetch Quest",
      "id": 8245,
      "consoleId": 65,
      "consoleName": "TIC-80",
      "imageIcon": "/Images/093224.png",
      "numAchievements": 0,
      "numLeaderboards": 0,
      "points": 0,
      "dateModified": null,
      "forumTopicId": null,
      "hashes": []
    },
    {
      "title": "FPS80",
      "id": 10923,
      "consoleId": 65,
      "consoleName": "TIC-80",
      "imageIcon": "/Images/093225.png",
      "numAchievements": 0,
      "numLeaderboards": 0,
      "points": 0,
      "dateModified": null,
      "forumTopicId": null,
      "hashes": []
    },
    {
      "title": "Miko Blade",
      "id": 8244,
      "consoleId": 65,
      "consoleName": "TIC-80",
      "imageIcon": "/Images/093196.png",
      "numAchievements": 0,
      "numLeaderboards": 0,
      "points": 0,
      "dateModified": null,
      "forumTopicId": null,
      "hashes": []
    },
    {
      "title": "Minetic",
      "id": 10931,
      "consoleId": 65,
      "consoleName": "TIC-80",
      "imageIcon": "/Images/093226.png",
      "numAchievements": 0,
      "numLeaderboards": 0,
      "points": 0,
      "dateModified": null,
      "forumTopicId": null,
      "hashes": []
    },
    {
      "title": "Rayportal",
      "id": 8212,
      "consoleId": 65,
      "consoleName": "TIC-80",
      "imageIcon": "/Images/093227.png",
      "numAchievements": 0,
      "numLeaderboards": 0,
      "points": 0,
      "dateModified": null,
      "forumTopicId": null,
      "hashes": []
    },
    {
      "title": "Rebound 2: Electric Boogaloo",
      "id": 10937,
      "consoleId": 65,
      "consoleName": "TIC-80",
      "imageIcon": "/Images/093228.png",
      "numAchievements": 0,
      "numLeaderboards": 0,
      "points": 0,
      "dateModified": null,
      "forumTopicId": null,
      "hashes": []
    },
    {
      "title": "Secret Agents",
      "id": 10938,
      "consoleId": 65,
      "consoleName": "TIC-80",
      "imageIcon": "/Images/093229.png",
      "numAchievements": 0,
      "numLeaderboards": 0,
      "points": 0,
      "dateModified": null,
      "forumTopicId": null,
      "hashes": []
    },
    {
      "title": "Shadow Over the Twelve Lands",
      "id": 10936,
      "consoleId": 65,
      "consoleName": "TIC-80",
      "imageIcon": "/Images/093230.png",
      "numAchievements": 0,
      "numLeaderboards": 0,
      "points": 0,
      "dateModified": null,
      "forumTopicId": null,
      "hashes": []
    },
    {
      "title": "Space Thing",
      "id": 8242,
      "consoleId": 65,
      "consoleName": "TIC-80",
      "imageIcon": "/Images/093232.png",
      "numAchievements": 0,
      "numLeaderboards": 0,
      "points": 0,
      "dateModified": null,
      "forumTopicId": null,
      "hashes": []
    },
    {
      "title": "Stele",
      "id": 10919,
      "consoleId": 65,
      "consoleName": "TIC-80",
      "imageIcon": "/Images/093233.png",
      "numAchievements": 0,
      "numLeaderboards": 0,
      "points": 0,
      "dateModified": null,
      "forumTopicId": null,
      "hashes": []
    },
    {
      "title": "Super Meat Boy TIC-80 Demake",
      "id": 10930,
      "consoleId": 65,
      "consoleName": "TIC-80",
      "imageIcon": "/Images/093240.png",
      "numAchievements": 0,
      "numLeaderboards": 0,
      "points": 0,
      "dateModified": null,
      "forumTopicId": null,
      "hashes": []
    },
    {
      "title": "Supernova",
      "id": 10921,
      "consoleId": 65,
      "consoleName": "TIC-80",
      "imageIcon": "/Images/093239.png",
      "numAchievements": 0,
      "numLeaderboards": 0,
      "points": 0,
      "dateModified": null,
      "forumTopicId": null,
      "hashes": []
    },
    {
      "title": "The Sky House",
      "id": 8153,
      "consoleId": 65,
      "consoleName": "TIC-80",
      "imageIcon": "/Images/093231.png",
      "numAchievements": 0,
      "numLeaderboards": 0,
      "points": 0,
      "dateModified": null,
      "forumTopicId": null,
      "hashes": []
    },
    {
      "title": "Tiny Dungeon",
      "id": 8235,
      "consoleId": 65,
      "consoleName": "TIC-80",
      "imageIcon": "/Images/093238.png",
      "numAchievements": 0,
      "numLeaderboards": 0,
      "points": 0,
      "dateModified": null,
      "forumTopicId": null,
      "hashes": []
    },
    {
      "title": "Turns of War",
      "id": 10932,
      "consoleId": 65,
      "consoleName": "TIC-80",
      "imageIcon": "/Images/093237.png",
      "numAchievements": 0,
      "numLeaderboards": 0,
      "points": 0,
      "dateModified": null,
      "forumTopicId": null,
      "hashes": []
    },
    {
      "title": "Witchem Up",
      "id": 10935,
      "consoleId": 65,
      "consoleName": "TIC-80",
      "imageIcon": "/Images/093236.png",
      "numAchievements": 0,
      "numLeaderboards": 0,
      "points": 0,
      "dateModified": null,
      "forumTopicId": null,
      "hashes": []
    },
    {
      "title": "Wolf-80",
      "id": 10910,
      "consoleId": 65,
      "consoleName": "TIC-80",
      "imageIcon": "/Images/093234.png",
      "numAchievements": 0,
      "numLeaderboards": 0,
      "points": 0,
      "dateModified": null,
      "forumTopicId": null,
      "hashes": []
    }
  ],
  "hashMap": {},
  "systemId": 65,
  "systemName": "TIC-80"
}